MANIFEST.in
README.rst
setup.py
dodge/__init__.py
dodge/conversion.py
dodge/data.py
dodge.egg-info/PKG-INFO
dodge.egg-info/SOURCES.txt
dodge.egg-info/dependency_links.txt
dodge.egg-info/top_level.txt