Metadata-Version: 1.1
Name: dodge
Version: 0.1.7
Summary: Create data objects that can be easily converted to and from dicts suitable for use as JSON
Home-page: http://github.com/mwilliamson/dodge.py
Author: Michael Williamson
Author-email: mike@zwobble.org
License: UNKNOWN
Keywords: data object serialise serialisation json
Platform: UNKNOWN
Classifier: Development Status :: 4 - Beta
Classifier: Intended Audience :: Developers
Classifier: License :: OSI Approved :: BSD License
Classifier: Programming Language :: Python
Classifier: Programming Language :: Python :: 2
Classifier: Programming Language :: Python :: 2.6
Classifier: Programming Language :: Python :: 2.7
Classifier: Programming Language :: Python :: 3
Classifier: Programming Language :: Python :: 3.2
Classifier: Programming Language :: Python :: 3.3
Classifier: Programming Language :: Python :: 3.4
Classifier: Operating System :: OS Independent
